adafruit_thermistor.py
adafruit_circuitpython_thermistor-3.4.16.dist-info/licenses/LICENSE
adafruit_circuitpython_thermistor-3.4.16.dist-info/METADATA
adafruit_circuitpython_thermistor-3.4.16.dist-info/WHEEL
adafruit_circuitpython_thermistor-3.4.16.dist-info/top_level.txt
adafruit_circuitpython_thermistor-3.4.16.dist-info/RECORD
